helloworld/__init__.py
helloworld/helloworld.py
nickffs_example_pkg-0.0.5.dist-info/LICENSE
nickffs_example_pkg-0.0.5.dist-info/METADATA
nickffs_example_pkg-0.0.5.dist-info/WHEEL
nickffs_example_pkg-0.0.5.dist-info/top_level.txt
nickffs_example_pkg-0.0.5.dist-info/RECORD
