Metadata-Version: 2.1
Name: nickffs-example-pkg
Version: 0.0.5
Summary: A template to create other PyPi packages.
Home-page: https://github.com/Bhavnicksm/pypi-packaging-template
Author: bhavnicksm
Author-email: bhavnicksm@gmail.com
License: UNKNOWN
Project-URL: Bug Tracker, https://github.com/Bhavnicksm/pypi-packaging-template/issues
Keywords: template
Platform: UNKNOWN
Classifier: Programming Language :: Python :: 3
Classifier: License :: OSI Approved :: MIT License
Classifier: Operating System :: OS Independent
Requires-Python: >=3.6
